dynamicrendergrpc/Core/Config.py
dynamicrendergrpc/Core/Dynamic.py
dynamicrendergrpc/Core/Tools.py
dynamicrendergrpc/Core/TypeAddition.py
dynamicrendergrpc/Core/TypeFooter.py
dynamicrendergrpc/Core/TypeForward.py
dynamicrendergrpc/Core/TypeHeader.py
dynamicrendergrpc/Core/TypeMajor.py
dynamicrendergrpc/Core/TypeText.py
dynamicrendergrpc/Core/TypeTopic.py
dynamicrendergrpc/Core/__init__.py
dynamicrendergrpc/Static/Cache/Emoji/keep
dynamicrendergrpc/Static/Cache/Face/keep
dynamicrendergrpc/Static/Cache/Pendant/keep
dynamicrendergrpc/Static/Font/HanaMinA.ttf
dynamicrendergrpc/Static/Font/Unifont.ttf
dynamicrendergrpc/Static/Font/nte.ttf
dynamicrendergrpc/Static/Picture/2233.jpg
dynamicrendergrpc/Static/Picture/article.png
dynamicrendergrpc/Static/Picture/bell.png
dynamicrendergrpc/Static/Picture/big_vip.png
dynamicrendergrpc/Static/Picture/bilibili.png
dynamicrendergrpc/Static/Picture/check.png
dynamicrendergrpc/Static/Picture/course.png
dynamicrendergrpc/Static/Picture/dsj.png
dynamicrendergrpc/Static/Picture/dy.png
dynamicrendergrpc/Static/Picture/enter.png
dynamicrendergrpc/Static/Picture/fj.png
dynamicrendergrpc/Static/Picture/gd.png
dynamicrendergrpc/Static/Picture/guild.png
dynamicrendergrpc/Static/Picture/icon_vote.png
dynamicrendergrpc/Static/Picture/jlp.png
dynamicrendergrpc/Static/Picture/link.png
dynamicrendergrpc/Static/Picture/live.png
dynamicrendergrpc/Static/Picture/look.png
dynamicrendergrpc/Static/Picture/lottery.png
dynamicrendergrpc/Static/Picture/mall_ic_collect_share_night.png
dynamicrendergrpc/Static/Picture/more.png
dynamicrendergrpc/Static/Picture/new_topic.png
dynamicrendergrpc/Static/Picture/official_blue.png
dynamicrendergrpc/Static/Picture/official_yellow.png
dynamicrendergrpc/Static/Picture/om.png
dynamicrendergrpc/Static/Picture/play.png
dynamicrendergrpc/Static/Picture/play2.png
dynamicrendergrpc/Static/Picture/small_vip.png
dynamicrendergrpc/Static/Picture/taobao.png
dynamicrendergrpc/Static/Picture/tg.png
dynamicrendergrpc-1.1.0.dist-info/WHEEL
dynamicrendergrpc-1.1.0.dist-info/METADATA
dynamicrendergrpc-1.1.0.dist-info/RECORD
