Metadata-Version: 2.1
Name: dynamicrendergrpc
Version: 1.1.0
Summary: 
Author: DMC
Author-email: lzxder@github.com
Requires-Python: >=3.8,<4.0
Classifier: Programming Language :: Python :: 3
Classifier: Programming Language :: Python :: 3.8
Classifier: Programming Language :: Python :: 3.9
Classifier: Programming Language :: Python :: 3.10
Classifier: Programming Language :: Python :: 3.11
Requires-Dist: emoji (==1.6.3)
Requires-Dist: fonttools (>=4.33.3,<5.0.0)
Requires-Dist: httpx (>=0.23.0,<0.24.0)
Requires-Dist: loguru (>=0.6.0,<0.7.0)
Requires-Dist: opencv-python-headless (>=4.6.0,<5.0.0)
Requires-Dist: pillow (>=9.1.1,<10.0.0)
Requires-Dist: pydantic (>=1.9.1,<2.0.0)
Requires-Dist: qrcode (>=7.3.1,<8.0.0)
